fsl_pipe_gui/__init__.py
fsl_pipe_gui/all_panes.py
fsl_pipe_gui/placeholder_tab.py
fsl_pipe_gui/run.py
fsl_pipe_gui/selector_tab.py
fsl_pipe_gui/summary.py
fsl_pipe_gui/css/placeholder.css
fsl_pipe_gui/css/selector.css
fsl_pipe_gui-0.2.0.dist-info/METADATA
fsl_pipe_gui-0.2.0.dist-info/WHEEL
fsl_pipe_gui-0.2.0.dist-info/licenses/LICENSE
fsl_pipe_gui-0.2.0.dist-info/RECORD
