Metadata-Version: 2.4
Name: fsl-pipe-gui
Version: 0.2.0
Summary: Terminal-based GUI for fsl-pipe.
Project-URL: Homepage, https://git.fmrib.ox.ac.uk/ndcn0236/fsl-pipe-gui
Project-URL: Documentation, https://open.win.ox.ac.uk/pages/fsl/fsl-pipe
Project-URL: Repository, https://git.fmrib.ox.ac.uk/ndcn0236/fsl-pipe-gui
Project-URL: Issues, https://git.fmrib.ox.ac.uk/ndcn0236/fsl-pipe-gui/-/issues
Author-email: Michiel Cottaar <michiel.cottaar@ndcn.ox.ac.uk>
License: MIT License
License-File: LICENSE
Keywords: GUI,neuroimage,pipeline,textual
Requires-Python: >=3.10
Requires-Dist: file-tree>=1.5.1
Requires-Dist: fsl-pipe>=0.7
Requires-Dist: textual>=0.29
